lmos_openai_types/__init__.py
lmos_openai_types/py.typed
lmos_openai_types-0.1.0.dist-info/METADATA
lmos_openai_types-0.1.0.dist-info/WHEEL
lmos_openai_types-0.1.0.dist-info/entry_points.txt
lmos_openai_types-0.1.0.dist-info/licenses/LICENSE
lmos_openai_types-0.1.0.dist-info/RECORD
