Metadata-Version: 2.4
Name: lmos-openai-types
Version: 0.1.0
Summary: Add your description here
Author-email: TerminalMan <84923604+SecretiveShell@users.noreply.github.com>
License-File: LICENSE
Requires-Python: >=3.13
Requires-Dist: pydantic>=2.10.6
